ranged/__init__.py
ranged-0.0.1.dist-info/METADATA
ranged-0.0.1.dist-info/WHEEL
ranged-0.0.1.dist-info/licenses/LICENSE
ranged-0.0.1.dist-info/RECORD
