Metadata-Version: 2.1
Name: ranged
Version: 0.0.1
Summary: A package aimed at creating a more feature rich range
Project-URL: Homepage, https://github.com/deerawj/ranged
Project-URL: Bug Tracker, https://github.com/deerawj/ranged/issues
Author-email: Deera Wijesundara <deerawj@gmail.com>
License-File: LICENSE
Classifier: License :: OSI Approved :: MIT License
Classifier: Operating System :: OS Independent
Classifier: Programming Language :: Python :: 3
Requires-Python: >=3.7
